pyclacker/pyclacker.py
pyclacker/stack.py
pyclacker/stack_actions.py
pyclacker/version.py
pyclacker-1.1.1.dist-info/LICENSE
pyclacker-1.1.1.dist-info/METADATA
pyclacker-1.1.1.dist-info/WHEEL
pyclacker-1.1.1.dist-info/entry_points.txt
pyclacker-1.1.1.dist-info/top_level.txt
pyclacker-1.1.1.dist-info/RECORD
