Metadata-Version: 2.1
Name: pyclacker
Version: 1.1.1
Summary: Command line reverse polish notation (RPN) calculator.
Home-page: https://github.com/jtompkin/pyclacker
Author: Josh Tompkin
Author-email: jtompkin-dev@pm.me
License: MIT
Keywords: calculator,calc,reverse,polish,rpn
Classifier: Programming Language :: Python :: 3
Classifier: License :: OSI Approved :: MIT License
Requires-Python: >=3.10
License-File: LICENSE
